ippanel/__init__.py
ippanel/client.py
ippanel_python_sdk-0.1.0.dist-info/licenses/LICENSE
ippanel_python_sdk-0.1.0.dist-info/METADATA
ippanel_python_sdk-0.1.0.dist-info/WHEEL
ippanel_python_sdk-0.1.0.dist-info/top_level.txt
ippanel_python_sdk-0.1.0.dist-info/RECORD
